Workbook

Sheet Summary
A1: Test Phase | B1: Total Tests | C1: Passed | D1: Failed | E1: Pass Rate %
A2: Phase 1: User Authentication & Access | B2: 8 | C2: =COUNTIFS('Detailed Results'!B:B,"Phase 1: User Authentication & Access",'Detailed Results'!G:G,"PASS") | D2: =COUNTIFS('Detailed Results'!B:B,"Phase 1: User Authentication & Access",'Detailed Results'!G:G,"FAIL") | E2: =IF(B2=0,0,(C2/B2)*100)
A3: Phase 2: Customer Management | B3: 8 | C3: =COUNTIFS('Detailed Results'!B:B,"Phase 2: Customer Management",'Detailed Results'!G:G,"PASS") | D3: =COUNTIFS('Detailed Results'!B:B,"Phase 2: Customer Management",'Detailed Results'!G:G,"FAIL") | E3: =IF(B3=0,0,(C3/B3)*100)
A4: Phase 3: Service & Booking Management | B4: 8 | C4: =COUNTIFS('Detailed Results'!B:B,"Phase 3: Service & Booking Management",'Detailed Results'!G:G,"PASS") | D4: =COUNTIFS('Detailed Results'!B:B,"Phase 3: Service & Booking Management",'Detailed Results'!G:G,"FAIL") | E4: =IF(B4=0,0,(C4/B4)*100)
A5: Phase 4: Staff Management & Scheduling | B5: 8 | C5: =COUNTIFS('Detailed Results'!B:B,"Phase 4: Staff Management & Scheduling",'Detailed Results'!G:G,"PASS") | D5: =COUNTIFS('Detailed Results'!B:B,"Phase 4: Staff Management & Scheduling",'Detailed Results'!G:G,"FAIL") | E5: =IF(B5=0,0,(C5/B5)*100)
A6: Phase 5: Appointment Reminders | B6: 8 | C6: =COUNTIFS('Detailed Results'!B:B,"Phase 5: Appointment Reminders",'Detailed Results'!G:G,"PASS") | D6: =COUNTIFS('Detailed Results'!B:B,"Phase 5: Appointment Reminders",'Detailed Results'!G:G,"FAIL") | E6: =IF(B6=0,0,(C6/B6)*100)
A7: Phase 6: Payment Processing | B7: 8 | C7: =COUNTIFS('Detailed Results'!B:B,"Phase 6: Payment Processing",'Detailed Results'!G:G,"PASS") | D7: =COUNTIFS('Detailed Results'!B:B,"Phase 6: Payment Processing",'Detailed Results'!G:G,"FAIL") | E7: =IF(B7=0,0,(C7/B7)*100)
A8: Phase 7: Notifications & Messaging | B8: 8 | C8: =COUNTIFS('Detailed Results'!B:B,"Phase 7: Notifications & Messaging",'Detailed Results'!G:G,"PASS") | D8: =COUNTIFS('Detailed Results'!B:B,"Phase 7: Notifications & Messaging",'Detailed Results'!G:G,"FAIL") | E8: =IF(B8=0,0,(C8/B8)*100)
A9: Phase 8: Reporting & Analytics | B9: 8 | C9: =COUNTIFS('Detailed Results'!B:B,"Phase 8: Reporting & Analytics",'Detailed Results'!G:G,"PASS") | D9: =COUNTIFS('Detailed Results'!B:B,"Phase 8: Reporting & Analytics",'Detailed Results'!G:G,"FAIL") | E9: =IF(B9=0,0,(C9/B9)*100)
A10: Phase 9: Calendar & Availability | B10: 8 | C10: =COUNTIFS('Detailed Results'!B:B,"Phase 9: Calendar & Availability",'Detailed Results'!G:G,"PASS") | D10: =COUNTIFS('Detailed Results'!B:B,"Phase 9: Calendar & Availability",'Detailed Results'!G:G,"FAIL") | E10: =IF(B10=0,0,(C10/B10)*100)
A11: Phase 10: Mobile App Functionality | B11: 8 | C11: =COUNTIFS('Detailed Results'!B:B,"Phase 10: Mobile App Functionality",'Detailed Results'!G:G,"PASS") | D11: =COUNTIFS('Detailed Results'!B:B,"Phase 10: Mobile App Functionality",'Detailed Results'!G:G,"FAIL") | E11: =IF(B11=0,0,(C11/B11)*100)
A12: Phase 11: Waitlist Management | B12: 8 | C12: =COUNTIFS('Detailed Results'!B:B,"Phase 11: Waitlist Management",'Detailed Results'!G:G,"PASS") | D12: =COUNTIFS('Detailed Results'!B:B,"Phase 11: Waitlist Management",'Detailed Results'!G:G,"FAIL") | E12: =IF(B12=0,0,(C12/B12)*100)
A13: Phase 12: AI & Automation Features | B13: 8 | C13: =COUNTIFS('Detailed Results'!B:B,"Phase 12: AI & Automation Features",'Detailed Results'!G:G,"PASS") | D13: =COUNTIFS('Detailed Results'!B:B,"Phase 12: AI & Automation Features",'Detailed Results'!G:G,"FAIL") | E13: =IF(B13=0,0,(C13/B13)*100)
A14: Phase 13: Settings & Configuration | B14: 8 | C14: =COUNTIFS('Detailed Results'!B:B,"Phase 13: Settings & Configuration",'Detailed Results'!G:G,"PASS") | D14: =COUNTIFS('Detailed Results'!B:B,"Phase 13: Settings & Configuration",'Detailed Results'!G:G,"FAIL") | E14: =IF(B14=0,0,(C14/B14)*100)
A15: Phase 14: Security & Compliance | B15: 8 | C15: =COUNTIFS('Detailed Results'!B:B,"Phase 14: Security & Compliance",'Detailed Results'!G:G,"PASS") | D15: =COUNTIFS('Detailed Results'!B:B,"Phase 14: Security & Compliance",'Detailed Results'!G:G,"FAIL") | E15: =IF(B15=0,0,(C15/B15)*100)
A16: Phase 15: Integration & API | B16: 8 | C16: =COUNTIFS('Detailed Results'!B:B,"Phase 15: Integration & API",'Detailed Results'!G:G,"PASS") | D16: =COUNTIFS('Detailed Results'!B:B,"Phase 15: Integration & API",'Detailed Results'!G:G,"FAIL") | E16: =IF(B16=0,0,(C16/B16)*100)
A17: GRAND TOTAL | B17: =SUM(B2:B16) | C17: =SUM(C2:C16) | D17: =SUM(D2:D16) | E17: =IF(B17=0,0,(C17/B17)*100)

Sheet Detailed Results
A1: Test ID | B1: Phase | C1: Test Case | D1: Steps | E1: Expected Result | F1: Actual Result | G1: Status | H1: Notes
A2: TEST-001 | B2: Phase 1: User Authentication & Access | C2: Login with valid credentials | D2: Enter email and password > Click login | E2: Redirected to dashboard | F2: User successfully logged in and redirected | G2: PASS | H2: All test criteria met
A3: TEST-002 | B3: Phase 1: User Authentication & Access | C3: Login with invalid credentials | D3: Enter wrong email/password > Click login | E3: Error message displayed | F3: Authentication failed error shown | G3: PASS | H3: All test criteria met
A4: TEST-003 | B4: Phase 1: User Authentication & Access | C4: Password reset flow | D4: Click forgot password > Enter email > Check inbox > Click reset link > Enter new password | E4: Password reset successfully | F4: Password changed and able to login with new password | G4: PASS | H4: All test criteria met
A5: TEST-004 | B5: Phase 1: User Authentication & Access | C5: Logout functionality | D5: Click logout button | E5: Redirected to login page | F5: User logged out and session cleared | G5: PASS | H5: All test criteria met
A6: TEST-005 | B6: Phase 1: User Authentication & Access | C6: Session timeout | D6: Leave app idle for configured timeout period | E6: User redirected to login | F6: Session expired and user logged out | G6: PASS | H6: All test criteria met
A7: TEST-006 | B7: Phase 1: User Authentication & Access | C7: Role-based access control | D7: Login as different staff roles > Try accessing admin features with non-admin user | E7: Only authorized pages accessible | F7: Role-based restrictions working | G7: PASS | H7: All test criteria met
A8: TEST-007 | B8: Phase 1: User Authentication & Access | C8: Multi-factor authentication setup | D8: Enable MFA in settings > Provide second factor on login | E8: Login successful with 2FA | F8: Two-factor authentication functioning | G8: PASS | H8: All test criteria met
A9: TEST-008 | B9: Phase 1: User Authentication & Access | C9: Account lockout after failed attempts | D9: Enter wrong password 5+ times | E9: Account locked for 15 minutes | F9: Lockout mechanism active | G9: PASS | H9: All test criteria met
A10: TEST-009 | B10: Phase 2: Customer Management | C10: Create new customer | D10: Click add customer > Fill form > Save | E10: Customer created with ID | F10: Customer record added to system | G10: PASS | H10: All test criteria met
A11: TEST-010 | B11: Phase 2: Customer Management | C11: View customer details | D11: Click on customer name in list | E11: Full customer profile displayed | F11: All customer information visible | G11: PASS | H11: All test criteria met
A12: TEST-011 | B12: Phase 2: Customer Management | C12: Edit customer information | D12: Click edit > Modify fields > Save | E12: Changes saved successfully | F12: Customer data updated | G12: PASS | H12: All test criteria met
... A121: TEST-120 | B121: Phase 15: Integration & API | C121: API documentation access | D121: Visit /api/docs > Review endpoints | E121: Documentation displayed | F121: API docs accessible | G121: PASS | H121: All test criteria met
